modules/__init__.py
modules/auth.py
modules/exceptions.py
modules/client/__init__.py
modules/client/protocol.py
modules/host/__init__.py
modules/host/protocol.py
modules/host/sessions.py
voolu-0.0.11.data/scripts/vacc.py
voolu-0.0.11.data/scripts/vcp.py
voolu-0.0.11.data/scripts/vhost.py
voolu-0.0.11.data/scripts/vsh.py
voolu-0.0.11.dist-info/METADATA
voolu-0.0.11.dist-info/WHEEL
voolu-0.0.11.dist-info/dependency_links.txt
voolu-0.0.11.dist-info/entry_points.txt
voolu-0.0.11.dist-info/top_level.txt
voolu-0.0.11.dist-info/RECORD
