Metadata-Version: 2.1
Name: voolu
Version: 0.0.11
Summary: SSH is so last year.
Home-page: https://github.com/voolu/vcli
Author: Voolu Cloud
Author-email: support@voolu.io
License: MIT
Platform: UNKNOWN
Classifier: License :: OSI Approved :: MIT License
Classifier: Programming Language :: Python :: 3.7
Requires-Python: >=3.7
Requires-Dist: httpx
Requires-Dist: click
Requires-Dist: inquirer
